healpix_alchemy/__init__.py
healpix_alchemy/constants.py
healpix_alchemy/func.py
healpix_alchemy/types.py
healpix_alchemy-1.1.0.dist-info/LICENSE
healpix_alchemy-1.1.0.dist-info/METADATA
healpix_alchemy-1.1.0.dist-info/WHEEL
healpix_alchemy-1.1.0.dist-info/RECORD
