Metadata-Version: 2.1
Name: healpix-alchemy
Version: 1.1.0
Summary: SQLAlchemy extensions for HEALPix spatially indexed astronomy data
Home-page: https://github.com/skyportal/healpix-alchemy
License: BSD-3-Clause
Author: Leo Singer
Author-email: leo.singer@ligo.org
Requires-Python: >=3.9,<4.0
Classifier: Development Status :: 4 - Beta
Classifier: License :: OSI Approved :: BSD License
Classifier: Programming Language :: Python :: 3
Classifier: Programming Language :: Python :: 3.9
Classifier: Programming Language :: Python :: 3.10
Classifier: Programming Language :: Python :: 3.11
Classifier: Programming Language :: Python :: 3.12
Classifier: Topic :: Database
Classifier: Topic :: Scientific/Engineering :: Astronomy
Requires-Dist: astropy
Requires-Dist: astropy_healpix
Requires-Dist: mocpy (>=0.12.2)
Requires-Dist: sqlalchemy (>=1.4)
Project-URL: Repository, https://github.com/skyportal/healpix-alchemy
